seedrapi/__init__.py
seedrapi/api.py
seedrapi/api_async.py
seedrapi/errors.py
seedrapi-1.0.dist-info/LICENSE
seedrapi-1.0.dist-info/METADATA
seedrapi-1.0.dist-info/WHEEL
seedrapi-1.0.dist-info/top_level.txt
seedrapi-1.0.dist-info/RECORD
