Metadata-Version: 2.1
Name: seedrapi
Version: 1.0
Summary: API wrapper for seedrapi.cc
Home-page: https://github.com/Spratiher9/Seedr-Client
Author: Souvik Pratiher
Author-email: spratiher9@gmail.com
License: MIT License
Download-URL: https://github.com/Spratiher9/Seedr-Client/releases/tag/v1.0
Keywords: seedrapi,seedrapi-api,seedrapi.cc,seedrapi-async,seedrapi-python-client
Platform: UNKNOWN
License-File: LICENSE
Requires-Dist: anyio
Requires-Dist: certifi
Requires-Dist: charset-normalizer
Requires-Dist: h11
Requires-Dist: httpcore
Requires-Dist: httpx
Requires-Dist: idna
Requires-Dist: requests
Requires-Dist: rfc3986
Requires-Dist: sniffio
Requires-Dist: urllib3
Requires-Dist: wheel
